{
  "global": {
    "fontSizes": {
      "base": {
        "value": "1rem",
        "type": "fontSizes"
      },
      "lg": {
        "value": "1.25rem",
        "type": "fontSizes"
      },
      "xl": {
        "value": "1.75rem",
        "type": "fontSizes"
      },
      "2xl": {
        "value": "2.25rem",
        "type": "fontSizes"
      },
      "3xl": {
        "value": "2.75rem",
        "type": "fontSizes"
      },
      "4xl": {
        "value": "3.25rem",
        "type": "fontSizes"
      },
      "5xl": {
        "value": "7rem",
        "type": "fontSizes"
      },
      "sm": {
        "value": "0.9rem",
        "type": "fontSizes"
      },
      "xs": {
        "value": "0.75rem",
        "type": "fontSizes"
      }
    },
    "fontFamilies": {
      "body": {
        "value": "Roboto",
        "type": "fontFamilies"
      },
      "heading": {
        "value": "Inter",
        "type": "fontFamilies"
      }
    },
    "fontWeights": {
      "regular": {
        "value": "Regular",
        "type": "fontWeights"
      },
      "bold": {
        "value": "Bold",
        "type": "fontWeights"
      }
    },
    "lineHeights": {
      "0": {
        "value": "160%",
        "type": "lineHeights"
      },
      "lg": {
        "value": "160%",
        "type": "lineHeights"
      },
      "md": {
        "value": "Auto",
        "type": "lineHeights"
      },
      "sm": {
        "value": "120%",
        "type": "lineHeights"
      },
      "xs": {
        "value": "100%",
        "type": "lineHeights"
      },
      "2xs": {
        "value": "80%",
        "type": "lineHeights"
      }
    },
    "paragraphSpacing": {
      "sm": {
        "value": "0.5em",
        "type": "paragraphSpacing"
      },
      "md": {
        "value": "1em",
        "type": "paragraphSpacing"
      },
      "lg": {
        "value": "2em",
        "type": "paragraphSpacing"
      }
    },
    "letterSpacing": {
      "base": {
        "value": "0%",
        "type": "letterSpacing"
      },
      "lg": {
        "value": "10%",
        "type": "letterSpacing"
      },
      "sm": {
        "value": "-3%",
        "type": "letterSpacing"
      }
    },
    "sizing": {
      "sm": {
        "value": "16",
        "type": "sizing"
      },
      "md": {
        "value": "32",
        "type": "sizing"
      },
      "lg": {
        "value": "64",
        "type": "sizing"
      }
    },
    "spacing": {
      "sm": {
        "value": "8",
        "type": "spacing"
      },
      "md": {
        "value": "16",
        "type": "spacing"
      },
      "lg": {
        "value": "32",
        "type": "spacing"
      },
      "xl": {
        "value": "64",
        "type": "spacing"
      }
    },
    "h1": {
      "bold": {
        "value": {
          "fontFamily": "{fontFamilies.heading}",
          "fontWeight": "{fontWeights.bold}",
          "lineHeight": "{lineHeights.xs}",
          "fontSize": "{fontSizes.4xl}",
          "letterSpacing": "{letterSpacing.sm}",
          "paragraphSpacing": "{p-spacing.xs}",
          "textDecoration": "none",
          "textCase": "none"
        },
        "type": "typography",
        "description": ""
      },
      "regular": {
        "value": {
          "fontFamily": "{fontFamilies.heading}",
          "fontWeight": "{fontWeights.regular}",
          "lineHeight": "{lineHeights.xs}",
          "fontSize": "{fontSizes.4xl}",
          "letterSpacing": "{letterSpacing.sm}",
          "paragraphSpacing": "{p-spacing.xs}",
          "textDecoration": "none",
          "textCase": "none"
        },
        "type": "typography",
        "description": ""
      }
    },
    "h2": {
      "bold": {
        "value": {
          "fontFamily": "{fontFamilies.heading}",
          "fontWeight": "{fontWeights.bold}",
          "lineHeight": "{lineHeights.xs}",
          "fontSize": "{fontSizes.3xl}",
          "letterSpacing": "{letterSpacing.sm}",
          "paragraphSpacing": "{p-spacing.xs}",
          "textDecoration": "none",
          "textCase": "none"
        },
        "type": "typography",
        "description": ""
      },
      "regular": {
        "value": {
          "fontFamily": "{fontFamilies.heading}",
          "fontWeight": "{fontWeights.regular}",
          "lineHeight": "{lineHeights.xs}",
          "fontSize": "{fontSizes.3xl}",
          "letterSpacing": "{letterSpacing.sm}",
          "paragraphSpacing": "{p-spacing.xs}",
          "textDecoration": "none",
          "textCase": "none"
        },
        "type": "typography",
        "description": ""
      }
    },
    "h3": {
      "bold": {
        "value": {
          "fontFamily": "{fontFamilies.heading}",
          "fontWeight": "{fontWeights.bold}",
          "lineHeight": "{lineHeights.xs}",
          "fontSize": "{fontSizes.2xl}",
          "letterSpacing": "{letterSpacing.sm}",
          "paragraphSpacing": "{p-spacing.xs}",
          "textDecoration": "none",
          "textCase": "none"
        },
        "type": "typography",
        "description": ""
      },
      "regular": {
        "value": {
          "fontFamily": "{fontFamilies.heading}",
          "fontWeight": "{fontWeights.regular}",
          "lineHeight": "{lineHeights.xs}",
          "fontSize": "{fontSizes.2xl}",
          "letterSpacing": "{letterSpacing.sm}",
          "paragraphSpacing": "{p-spacing.xs}",
          "textDecoration": "none",
          "textCase": "none"
        },
        "type": "typography",
        "description": ""
      }
    },
    "h4": {
      "bold": {
        "value": {
          "fontFamily": "{fontFamilies.heading}",
          "fontWeight": "{fontWeights.bold}",
          "lineHeight": "{lineHeights.xs}",
          "fontSize": "{fontSizes.xl}",
          "letterSpacing": "{letterSpacing.sm}",
          "paragraphSpacing": "{p-spacing.xs}",
          "textDecoration": "none",
          "textCase": "none"
        },
        "type": "typography",
        "description": ""
      },
      "regular": {
        "value": {
          "fontFamily": "{fontFamilies.heading}",
          "fontWeight": "{fontWeights.regular}",
          "lineHeight": "{lineHeights.xs}",
          "fontSize": "{fontSizes.xl}",
          "letterSpacing": "{letterSpacing.sm}",
          "paragraphSpacing": "{p-spacing.xs}",
          "textDecoration": "none",
          "textCase": "none"
        },
        "type": "typography",
        "description": ""
      }
    },
    "display": {
      "bold": {
        "value": {
          "fontFamily": "{fontFamilies.heading}",
          "fontWeight": "{fontWeights.bold}",
          "lineHeight": "{lineHeights.xs}",
          "fontSize": "{fontSizes.5xl}",
          "letterSpacing": "{letterSpacing.sm}",
          "paragraphSpacing": "{p-spacing.xs}",
          "textDecoration": "none",
          "textCase": "none"
        },
        "type": "typography",
        "description": ""
      },
      "regular": {
        "value": {
          "fontFamily": "{fontFamilies.heading}",
          "fontWeight": "{fontWeights.regular}",
          "lineHeight": "{lineHeights.xs}",
          "fontSize": "{fontSizes.5xl}",
          "letterSpacing": "{letterSpacing.sm}",
          "paragraphSpacing": "{p-spacing.xs}",
          "textDecoration": "none",
          "textCase": "none"
        },
        "type": "typography",
        "description": ""
      }
    },
    "p": {
      "regular": {
        "value": {
          "fontFamily": "{fontFamilies.body}",
          "fontWeight": "{fontWeights.regular}",
          "lineHeight": "{lineHeights.lg}",
          "fontSize": "{fontSizes.base}",
          "letterSpacing": "{letterSpacing.base}",
          "paragraphSpacing": "{paragraphSpacing.sm}",
          "textDecoration": "none",
          "textCase": "none"
        },
        "type": "typography"
      }
    }
  }
}